Metadata-Version: 2.1
Name: funcStats
Version: 0.1.0
Summary: A module that helps to evaluate functions when some tests are needed
Author: Elemental (Tom Neto)
Author-email: <info@elemental.run>
Keywords: python,functions,cronometer,crono,meter,evaluate functions
Classifier: Development Status :: 1 - Planning
Classifier: Intended Audience :: Developers
Classifier: Programming Language :: Python :: 3.11
Classifier: Operating System :: Unix
Classifier: Operating System :: MacOS :: MacOS X
Classifier: Operating System :: Microsoft :: Windows
License-File: LICENSE
